{
    "type": "FeatureCollection",
    "metadata": {
        "generated": 1650103680000,
        "url": "https://earthquake.usgs.gov/earthquakes/feed/v1.0/summary/significant_week.geojson",
        "title": "USGS Significant Earthquakes, Past Week",
        "status": 200,
        "api": "1.10.3",
        "count": 2
    },
    "features": [
        {
            "type": "Feature",
            "properties": {
                "mag": 4.55,
                "place": "20km W of El Sauzal, B.C., MX",
                "time": 1649997055980,
                "updated": 1650094593819,
                "tz": null,
                "url": "https://earthquake.usgs.gov/earthquakes/eventpage/ci40236864",
                "detail": "https://earthquake.usgs.gov/earthquakes/feed/v1.0/detail/ci40236864.geojson",
                "felt": 4578,
                "cdi": 4.7,
                "mmi": 4.206,
                "alert": "green",
                "status": "reviewed",
                "tsunami": 1,
                "sig": 788,
                "net": "ci",
                "code": "40236864",
                "ids": ",ci40236864,at00rad5vi,us7000h2fb,ew1649997070,",
                "sources": ",ci,at,us,ew,",
                "types": ",dyfi,impact-link,losspager,moment-tensor,nearby-cities,origin,phase-data,scitech-link,shake-alert,shakemap,",
                "nst": 27,
                "dmin": 0.2038,
                "rms": 0.23,
                "gap": 234,
                "magType": "mw",
                "type": "earthquake",
                "title": "M 4.6 - 20km W of El Sauzal, B.C., MX"
            },
            "geometry": {
                "type": "Point",
                "coordinates": [
                    -116.8925,
                    31.9305,
                    14.51
                ]
            },
            "id": "ci40236864"
        },
        {
            "type": "Feature",
            "properties": {
                "mag": 6.3,
                "place": "64 km WSW of Norsup, Vanuatu",
                "time": 1649537557344,
                "updated": 1649624262406,
                "tz": null,
                "url": "https://earthquake.usgs.gov/earthquakes/eventpage/us7000h0yj",
                "detail": "https://earthquake.usgs.gov/earthquakes/feed/v1.0/detail/us7000h0yj.geojson",
                "felt": 9,
                "cdi": 7.9,
                "mmi": 5.174,
                "alert": "green",
                "status": "reviewed",
                "tsunami": 0,
                "sig": 618,
                "net": "us",
                "code": "7000h0yj",
                "ids": ",us7000h0yj,",
                "sources": ",us,",
                "types": ",dyfi,ground-failure,losspager,moment-tensor,origin,phase-data,shakemap,",
                "nst": null,
                "dmin": 0.93,
                "rms": 0.88,
                "gap": 33,
                "magType": "mww",
                "type": "earthquake",
                "title": "M 6.3 - 64 km WSW of Norsup, Vanuatu"
            },
            "geometry": {
                "type": "Point",
                "coordinates": [
                    166.8507,
                    -16.3181,
                    10
                ]
            },
            "id": "us7000h0yj"
        }
    ],
    "bbox": [
        -116.8925,
        -16.3181,
        10,
        166.8507,
        31.9305,
        14.51
    ]
}